simple_trigger_audit/__init__.py
simple_trigger_audit/admin.py
simple_trigger_audit/apps.py
simple_trigger_audit/middleware.py
simple_trigger_audit/models.py
simple_trigger_audit/signals.py
simple_trigger_audit/utils.py
simple_trigger_audit/migrations/0001_initial.py
simple_trigger_audit/migrations/0002_trigger_audit_entries_table.py
simple_trigger_audit/migrations/0003_trigger_audit_entry_creator_func.py
simple_trigger_audit/migrations/__init__.py
django_simple_trigger_audit-0.0.6.dist-info/LICENSE
django_simple_trigger_audit-0.0.6.dist-info/METADATA
django_simple_trigger_audit-0.0.6.dist-info/WHEEL
django_simple_trigger_audit-0.0.6.dist-info/top_level.txt
django_simple_trigger_audit-0.0.6.dist-info/RECORD
